snakepay/__init__.py
snakepay/snakepay.py
snakepay-0.1.1.dist-info/METADATA
snakepay-0.1.1.dist-info/WHEEL
snakepay-0.1.1.dist-info/top_level.txt
snakepay-0.1.1.dist-info/RECORD
